{"type":"Feature",
 "geometry":{"type":"Point","coordinates":[-121.0880000,38.2610000]},
 "properties":{"prmname":"RECH8",
 "description":"Artificial Recharge node",
 "type":"Junction",
 "inflows":null,
 "sinks":null,
 "flow":null}}
